{
  "type": "create:mixing",
  "ingredients": [
    {
      "tag": "cottage_industry:contains_quicksilver"
    },
    {
      "tag": "cottage_industry:contains_quicksilver"
    },
    {
      "tag": "cottage_industry:contains_quicksilver"
    },
    {
      "tag": "cottage_industry:contains_quicksilver"
    },
    {
      "tag": "cottage_industry:contains_quicksilver"
    },
    {
      "tag": "cottage_industry:contains_quicksilver"
    },
    {
      "tag": "cottage_industry:contains_quicksilver"
    },
    {
      "tag": "cottage_industry:contains_quicksilver"
    }
  ],
  "results": [
    {
      "fluid": "hexerei:quicksilver_fluid",
      "amount": 250
    }
  ]
}